decorators_cryptography/__init__.py
decorators_cryptography/decorators_cryptography.py
decorators_cryptography/exceptions.py
decorators_cryptography-0.1.0.dist-info/METADATA
decorators_cryptography-0.1.0.dist-info/WHEEL
decorators_cryptography-0.1.0.dist-info/RECORD
