Metadata-Version: 2.1
Name: decorators-cryptography
Version: 0.1.0
Summary: Decorators for encrypting/decrypting passed arguments
Home-page: https://github.com/kotorkovsciy/decorators-cryptography
Author: Kotorkovsciy
Author-email: kotorkovsciy@gmail.com
Requires-Python: >=3.10,<4.0
Classifier: Operating System :: OS Independent
Classifier: Programming Language :: Python :: 3
Classifier: Programming Language :: Python :: 3.10
Classifier: Programming Language :: Python :: 3.11
Requires-Dist: cryptography (>=41.0.1,<42.0.0)
Requires-Dist: pre-commit (>=3.3.3,<4.0.0)
Project-URL: Repository, https://github.com/kotorkovsciy/decorators-cryptography
